<annotation><folder>train</folder><filename>0d08bc31f.jpg</filename><size><width>1024</width><height>1024</height><depth>3</depth></size><object><name>wheat head</name><pose>Unspecified</pose><truncated>0</truncated><difficult>0</difficult><bndbox><xmin>537.0</xmin><ymin>837.0</ymin><xmax>622.0</xmax><ymax>913.0</ymax></bndbox></object><folder>train</folder><filename>0d08bc31f.jpg</filename><size><width>1024</width><height>1024</height><depth>3</depth></size><object><name>wheat head</name><pose>Unspecified</pose><truncated>0</truncated><difficult>0</difficult><bndbox><xmin>759.0</xmin><ymin>38.0</ymin><xmax>836.0</xmax><ymax>115.0</ymax></bndbox></object><folder>train</folder><filename>0d08bc31f.jpg</filename><size><width>1024</width><height>1024</height><depth>3</depth></size><object><name>wheat head</name><pose>Unspecified</pose><truncated>0</truncated><difficult>0</difficult><bndbox><xmin>765.0</xmin><ymin>222.0</ymin><xmax>847.0</xmax><ymax>279.0</ymax></bndbox></object><folder>train</folder><filename>0d08bc31f.jpg</filename><size><width>1024</width><height>1024</height><depth>3</depth></size><object><name>wheat head</name><pose>Unspecified</pose><truncated>0</truncated><difficult>0</difficult><bndbox><xmin>942.0</xmin><ymin>0.0</ymin><xmax>1024.0</xmax><ymax>48.0</ymax></bndbox></object><folder>train</folder><filename>0d08bc31f.jpg</filename><size><width>1024</width><height>1024</height><depth>3</depth></size><object><name>wheat head</name><pose>Unspecified</pose><truncated>0</truncated><difficult>0</difficult><bndbox><xmin>629.0</xmin><ymin>58.0</ymin><xmax>744.0</xmax><ymax>138.0</ymax></bndbox></object><folder>train</folder><filename>0d08bc31f.jpg</filename><size><width>1024</width><height>1024</height><depth>3</depth></size><object><name>wheat head</name><pose>Unspecified</pose><truncated>0</truncated><difficult>0</difficult><bndbox><xmin>801.0</xmin><ymin>184.0</ymin><xmax>883.0</xmax><ymax>245.0</ymax></bndbox></object><folder>train</folder><filename>0d08bc31f.jpg</filename><size><width>1024</width><height>1024</height><depth>3</depth></size><object><name>wheat head</name><pose>Unspecified</pose><truncated>0</truncated><difficult>0</difficult><bndbox><xmin>702.0</xmin><ymin>776.0</ymin><xmax>794.0</xmax><ymax>859.0</ymax></bndbox></object><folder>train</folder><filename>0d08bc31f.jpg</filename><size><width>1024</width><height>1024</height><depth>3</depth></size><object><name>wheat head</name><pose>Unspecified</pose><truncated>0</truncated><difficult>0</difficult><bndbox><xmin>542.0</xmin><ymin>883.0</ymin><xmax>650.0</xmax><ymax>952.0</ymax></bndbox></object><folder>train</folder><filename>0d08bc31f.jpg</filename><size><width>1024</width><height>1024</height><depth>3</depth></size><object><name>wheat head</name><pose>Unspecified</pose><truncated>0</truncated><difficult>0</difficult><bndbox><xmin>361.0</xmin><ymin>968.0</ymin><xmax>463.0</xmax><ymax>1024.0</ymax></bndbox></object><folder>train</folder><filename>0d08bc31f.jpg</filename><size><width>1024</width><height>1024</height><depth>3</depth></size><object><name>wheat head</name><pose>Unspecified</pose><truncated>0</truncated><difficult>0</difficult><bndbox><xmin>539.0</xmin><ymin>944.0</ymin><xmax>635.0</xmax><ymax>1024.0</ymax></bndbox></object><folder>train</folder><filename>0d08bc31f.jpg</filename><size><width>1024</width><height>1024</height><depth>3</depth></size><object><name>wheat head</name><pose>Unspecified</pose><truncated>0</truncated><difficult>0</difficult><bndbox><xmin>772.0</xmin><ymin>900.0</ymin><xmax>831.0</xmax><ymax>988.0</ymax></bndbox></object></annotation>