<annotation><folder>train</folder><filename>509a7a9b5.jpg</filename><size><width>1024</width><height>1024</height><depth>3</depth></size><object><name>wheat head</name><pose>Unspecified</pose><truncated>0</truncated><difficult>0</difficult><bndbox><xmin>823.0</xmin><ymin>114.0</ymin><xmax>954.0</xmax><ymax>209.0</ymax></bndbox></object><folder>train</folder><filename>509a7a9b5.jpg</filename><size><width>1024</width><height>1024</height><depth>3</depth></size><object><name>wheat head</name><pose>Unspecified</pose><truncated>0</truncated><difficult>0</difficult><bndbox><xmin>0.0</xmin><ymin>74.0</ymin><xmax>46.0</xmax><ymax>158.0</ymax></bndbox></object><folder>train</folder><filename>509a7a9b5.jpg</filename><size><width>1024</width><height>1024</height><depth>3</depth></size><object><name>wheat head</name><pose>Unspecified</pose><truncated>0</truncated><difficult>0</difficult><bndbox><xmin>0.0</xmin><ymin>922.0</ymin><xmax>115.0</xmax><ymax>979.0</ymax></bndbox></object><folder>train</folder><filename>509a7a9b5.jpg</filename><size><width>1024</width><height>1024</height><depth>3</depth></size><object><name>wheat head</name><pose>Unspecified</pose><truncated>0</truncated><difficult>0</difficult><bndbox><xmin>750.0</xmin><ymin>362.0</ymin><xmax>840.0</xmax><ymax>436.0</ymax></bndbox></object></annotation>