<annotation><folder>train</folder><filename>c07d3abee.jpg</filename><size><width>1024</width><height>1024</height><depth>3</depth></size><object><name>wheat head</name><pose>Unspecified</pose><truncated>0</truncated><difficult>0</difficult><bndbox><xmin>928.0</xmin><ymin>275.0</ymin><xmax>1024.0</xmax><ymax>363.0</ymax></bndbox></object><folder>train</folder><filename>c07d3abee.jpg</filename><size><width>1024</width><height>1024</height><depth>3</depth></size><object><name>wheat head</name><pose>Unspecified</pose><truncated>0</truncated><difficult>0</difficult><bndbox><xmin>925.0</xmin><ymin>460.0</ymin><xmax>1019.0</xmax><ymax>563.0</ymax></bndbox></object><folder>train</folder><filename>c07d3abee.jpg</filename><size><width>1024</width><height>1024</height><depth>3</depth></size><object><name>wheat head</name><pose>Unspecified</pose><truncated>0</truncated><difficult>0</difficult><bndbox><xmin>837.0</xmin><ymin>531.0</ymin><xmax>934.0</xmax><ymax>627.0</ymax></bndbox></object><folder>train</folder><filename>c07d3abee.jpg</filename><size><width>1024</width><height>1024</height><depth>3</depth></size><object><name>wheat head</name><pose>Unspecified</pose><truncated>0</truncated><difficult>0</difficult><bndbox><xmin>717.0</xmin><ymin>585.0</ymin><xmax>877.0</xmax><ymax>687.0</ymax></bndbox></object><folder>train</folder><filename>c07d3abee.jpg</filename><size><width>1024</width><height>1024</height><depth>3</depth></size><object><name>wheat head</name><pose>Unspecified</pose><truncated>0</truncated><difficult>0</difficult><bndbox><xmin>484.0</xmin><ymin>457.0</ymin><xmax>638.0</xmax><ymax>606.0</ymax></bndbox></object><folder>train</folder><filename>c07d3abee.jpg</filename><size><width>1024</width><height>1024</height><depth>3</depth></size><object><name>wheat head</name><pose>Unspecified</pose><truncated>0</truncated><difficult>0</difficult><bndbox><xmin>773.0</xmin><ymin>335.0</ymin><xmax>866.0</xmax><ymax>414.0</ymax></bndbox></object><folder>train</folder><filename>c07d3abee.jpg</filename><size><width>1024</width><height>1024</height><depth>3</depth></size><object><name>wheat head</name><pose>Unspecified</pose><truncated>0</truncated><difficult>0</difficult><bndbox><xmin>275.0</xmin><ymin>164.0</ymin><xmax>391.0</xmax><ymax>246.0</ymax></bndbox></object><folder>train</folder><filename>c07d3abee.jpg</filename><size><width>1024</width><height>1024</height><depth>3</depth></size><object><name>wheat head</name><pose>Unspecified</pose><truncated>0</truncated><difficult>0</difficult><bndbox><xmin>141.0</xmin><ymin>662.0</ymin><xmax>294.0</xmax><ymax>775.0</ymax></bndbox></object><folder>train</folder><filename>c07d3abee.jpg</filename><size><width>1024</width><height>1024</height><depth>3</depth></size><object><name>wheat head</name><pose>Unspecified</pose><truncated>0</truncated><difficult>0</difficult><bndbox><xmin>278.0</xmin><ymin>845.0</ymin><xmax>401.0</xmax><ymax>963.0</ymax></bndbox></object><folder>train</folder><filename>c07d3abee.jpg</filename><size><width>1024</width><height>1024</height><depth>3</depth></size><object><name>wheat head</name><pose>Unspecified</pose><truncated>0</truncated><difficult>0</difficult><bndbox><xmin>482.0</xmin><ymin>768.0</ymin><xmax>568.0</xmax><ymax>860.0</ymax></bndbox></object><folder>train</folder><filename>c07d3abee.jpg</filename><size><width>1024</width><height>1024</height><depth>3</depth></size><object><name>wheat head</name><pose>Unspecified</pose><truncated>0</truncated><difficult>0</difficult><bndbox><xmin>69.0</xmin><ymin>866.0</ymin><xmax>201.0</xmax><ymax>956.0</ymax></bndbox></object><folder>train</folder><filename>c07d3abee.jpg</filename><size><width>1024</width><height>1024</height><depth>3</depth></size><object><name>wheat head</name><pose>Unspecified</pose><truncated>0</truncated><difficult>0</difficult><bndbox><xmin>181.0</xmin><ymin>140.0</ymin><xmax>280.0</xmax><ymax>289.0</ymax></bndbox></object><folder>train</folder><filename>c07d3abee.jpg</filename><size><width>1024</width><height>1024</height><depth>3</depth></size><object><name>wheat head</name><pose>Unspecified</pose><truncated>0</truncated><difficult>0</difficult><bndbox><xmin>81.0</xmin><ymin>307.0</ymin><xmax>168.0</xmax><ymax>397.0</ymax></bndbox></object><folder>train</folder><filename>c07d3abee.jpg</filename><size><width>1024</width><height>1024</height><depth>3</depth></size><object><name>wheat head</name><pose>Unspecified</pose><truncated>0</truncated><difficult>0</difficult><bndbox><xmin>144.0</xmin><ymin>387.0</ymin><xmax>220.0</xmax><ymax>474.0</ymax></bndbox></object><folder>train</folder><filename>c07d3abee.jpg</filename><size><width>1024</width><height>1024</height><depth>3</depth></size><object><name>wheat head</name><pose>Unspecified</pose><truncated>0</truncated><difficult>0</difficult><bndbox><xmin>31.0</xmin><ymin>433.0</ymin><xmax>112.0</xmax><ymax>500.0</ymax></bndbox></object><folder>train</folder><filename>c07d3abee.jpg</filename><size><width>1024</width><height>1024</height><depth>3</depth></size><object><name>wheat head</name><pose>Unspecified</pose><truncated>0</truncated><difficult>0</difficult><bndbox><xmin>0.0</xmin><ymin>489.0</ymin><xmax>69.0</xmax><ymax>570.0</ymax></bndbox></object><folder>train</folder><filename>c07d3abee.jpg</filename><size><width>1024</width><height>1024</height><depth>3</depth></size><object><name>wheat head</name><pose>Unspecified</pose><truncated>0</truncated><difficult>0</difficult><bndbox><xmin>290.0</xmin><ymin>457.0</ymin><xmax>356.0</xmax><ymax>536.0</ymax></bndbox></object><folder>train</folder><filename>c07d3abee.jpg</filename><size><width>1024</width><height>1024</height><depth>3</depth></size><object><name>wheat head</name><pose>Unspecified</pose><truncated>0</truncated><difficult>0</difficult><bndbox><xmin>400.0</xmin><ymin>434.0</ymin><xmax>457.0</xmax><ymax>515.0</ymax></bndbox></object><folder>train</folder><filename>c07d3abee.jpg</filename><size><width>1024</width><height>1024</height><depth>3</depth></size><object><name>wheat head</name><pose>Unspecified</pose><truncated>0</truncated><difficult>0</difficult><bndbox><xmin>316.0</xmin><ymin>402.0</ymin><xmax>379.0</xmax><ymax>463.0</ymax></bndbox></object><folder>train</folder><filename>c07d3abee.jpg</filename><size><width>1024</width><height>1024</height><depth>3</depth></size><object><name>wheat head</name><pose>Unspecified</pose><truncated>0</truncated><difficult>0</difficult><bndbox><xmin>336.0</xmin><ymin>350.0</ymin><xmax>488.0</xmax><ymax>449.0</ymax></bndbox></object><folder>train</folder><filename>c07d3abee.jpg</filename><size><width>1024</width><height>1024</height><depth>3</depth></size><object><name>wheat head</name><pose>Unspecified</pose><truncated>0</truncated><difficult>0</difficult><bndbox><xmin>641.0</xmin><ymin>492.0</ymin><xmax>704.0</xmax><ymax>560.0</ymax></bndbox></object><folder>train</folder><filename>c07d3abee.jpg</filename><size><width>1024</width><height>1024</height><depth>3</depth></size><object><name>wheat head</name><pose>Unspecified</pose><truncated>0</truncated><difficult>0</difficult><bndbox><xmin>830.0</xmin><ymin>461.0</ymin><xmax>873.0</xmax><ymax>508.0</ymax></bndbox></object><folder>train</folder><filename>c07d3abee.jpg</filename><size><width>1024</width><height>1024</height><depth>3</depth></size><object><name>wheat head</name><pose>Unspecified</pose><truncated>0</truncated><difficult>0</difficult><bndbox><xmin>463.0</xmin><ymin>246.0</ymin><xmax>566.0</xmax><ymax>342.0</ymax></bndbox></object><folder>train</folder><filename>c07d3abee.jpg</filename><size><width>1024</width><height>1024</height><depth>3</depth></size><object><name>wheat head</name><pose>Unspecified</pose><truncated>0</truncated><difficult>0</difficult><bndbox><xmin>561.0</xmin><ymin>109.0</ymin><xmax>631.0</xmax><ymax>157.0</ymax></bndbox></object><folder>train</folder><filename>c07d3abee.jpg</filename><size><width>1024</width><height>1024</height><depth>3</depth></size><object><name>wheat head</name><pose>Unspecified</pose><truncated>0</truncated><difficult>0</difficult><bndbox><xmin>517.0</xmin><ymin>0.0</ymin><xmax>637.0</xmax><ymax>61.0</ymax></bndbox></object><folder>train</folder><filename>c07d3abee.jpg</filename><size><width>1024</width><height>1024</height><depth>3</depth></size><object><name>wheat head</name><pose>Unspecified</pose><truncated>0</truncated><difficult>0</difficult><bndbox><xmin>887.0</xmin><ymin>326.0</ymin><xmax>944.0</xmax><ymax>395.0</ymax></bndbox></object><folder>train</folder><filename>c07d3abee.jpg</filename><size><width>1024</width><height>1024</height><depth>3</depth></size><object><name>wheat head</name><pose>Unspecified</pose><truncated>0</truncated><difficult>0</difficult><bndbox><xmin>901.0</xmin><ymin>220.0</ymin><xmax>972.0</xmax><ymax>285.0</ymax></bndbox></object><folder>train</folder><filename>c07d3abee.jpg</filename><size><width>1024</width><height>1024</height><depth>3</depth></size><object><name>wheat head</name><pose>Unspecified</pose><truncated>0</truncated><difficult>0</difficult><bndbox><xmin>816.0</xmin><ymin>69.0</ymin><xmax>913.0</xmax><ymax>128.0</ymax></bndbox></object><folder>train</folder><filename>c07d3abee.jpg</filename><size><width>1024</width><height>1024</height><depth>3</depth></size><object><name>wheat head</name><pose>Unspecified</pose><truncated>0</truncated><difficult>0</difficult><bndbox><xmin>973.0</xmin><ymin>0.0</ymin><xmax>1024.0</xmax><ymax>60.0</ymax></bndbox></object><folder>train</folder><filename>c07d3abee.jpg</filename><size><width>1024</width><height>1024</height><depth>3</depth></size><object><name>wheat head</name><pose>Unspecified</pose><truncated>0</truncated><difficult>0</difficult><bndbox><xmin>771.0</xmin><ymin>0.0</ymin><xmax>912.0</xmax><ymax>39.0</ymax></bndbox></object><folder>train</folder><filename>c07d3abee.jpg</filename><size><width>1024</width><height>1024</height><depth>3</depth></size><object><name>wheat head</name><pose>Unspecified</pose><truncated>0</truncated><difficult>0</difficult><bndbox><xmin>846.0</xmin><ymin>18.0</ymin><xmax>921.0</xmax><ymax>73.0</ymax></bndbox></object><folder>train</folder><filename>c07d3abee.jpg</filename><size><width>1024</width><height>1024</height><depth>3</depth></size><object><name>wheat head</name><pose>Unspecified</pose><truncated>0</truncated><difficult>0</difficult><bndbox><xmin>380.0</xmin><ymin>611.0</ymin><xmax>565.0</xmax><ymax>709.0</ymax></bndbox></object><folder>train</folder><filename>c07d3abee.jpg</filename><size><width>1024</width><height>1024</height><depth>3</depth></size><object><name>wheat head</name><pose>Unspecified</pose><truncated>0</truncated><difficult>0</difficult><bndbox><xmin>536.0</xmin><ymin>714.0</ymin><xmax>599.0</xmax><ymax>780.0</ymax></bndbox></object><folder>train</folder><filename>c07d3abee.jpg</filename><size><width>1024</width><height>1024</height><depth>3</depth></size><object><name>wheat head</name><pose>Unspecified</pose><truncated>0</truncated><difficult>0</difficult><bndbox><xmin>763.0</xmin><ymin>763.0</ymin><xmax>855.0</xmax><ymax>827.0</ymax></bndbox></object><folder>train</folder><filename>c07d3abee.jpg</filename><size><width>1024</width><height>1024</height><depth>3</depth></size><object><name>wheat head</name><pose>Unspecified</pose><truncated>0</truncated><difficult>0</difficult><bndbox><xmin>774.0</xmin><ymin>885.0</ymin><xmax>844.0</xmax><ymax>956.0</ymax></bndbox></object><folder>train</folder><filename>c07d3abee.jpg</filename><size><width>1024</width><height>1024</height><depth>3</depth></size><object><name>wheat head</name><pose>Unspecified</pose><truncated>0</truncated><difficult>0</difficult><bndbox><xmin>918.0</xmin><ymin>868.0</ymin><xmax>997.0</xmax><ymax>915.0</ymax></bndbox></object><folder>train</folder><filename>c07d3abee.jpg</filename><size><width>1024</width><height>1024</height><depth>3</depth></size><object><name>wheat head</name><pose>Unspecified</pose><truncated>0</truncated><difficult>0</difficult><bndbox><xmin>573.0</xmin><ymin>873.0</ymin><xmax>655.0</xmax><ymax>991.0</ymax></bndbox></object><folder>train</folder><filename>c07d3abee.jpg</filename><size><width>1024</width><height>1024</height><depth>3</depth></size><object><name>wheat head</name><pose>Unspecified</pose><truncated>0</truncated><difficult>0</difficult><bndbox><xmin>470.0</xmin><ymin>899.0</ymin><xmax>534.0</xmax><ymax>942.0</ymax></bndbox></object><folder>train</folder><filename>c07d3abee.jpg</filename><size><width>1024</width><height>1024</height><depth>3</depth></size><object><name>wheat head</name><pose>Unspecified</pose><truncated>0</truncated><difficult>0</difficult><bndbox><xmin>419.0</xmin><ymin>935.0</ymin><xmax>514.0</xmax><ymax>1012.0</ymax></bndbox></object><folder>train</folder><filename>c07d3abee.jpg</filename><size><width>1024</width><height>1024</height><depth>3</depth></size><object><name>wheat head</name><pose>Unspecified</pose><truncated>0</truncated><difficult>0</difficult><bndbox><xmin>0.0</xmin><ymin>216.0</ymin><xmax>123.0</xmax><ymax>328.0</ymax></bndbox></object><folder>train</folder><filename>c07d3abee.jpg</filename><size><width>1024</width><height>1024</height><depth>3</depth></size><object><name>wheat head</name><pose>Unspecified</pose><truncated>0</truncated><difficult>0</difficult><bndbox><xmin>0.0</xmin><ymin>52.0</ymin><xmax>74.0</xmax><ymax>157.0</ymax></bndbox></object><folder>train</folder><filename>c07d3abee.jpg</filename><size><width>1024</width><height>1024</height><depth>3</depth></size><object><name>wheat head</name><pose>Unspecified</pose><truncated>0</truncated><difficult>0</difficult><bndbox><xmin>0.0</xmin><ymin>231.0</ymin><xmax>128.0</xmax><ymax>321.0</ymax></bndbox></object></annotation>